arpeggioportal/PortalSession.py
arpeggioportal/__init__.py
arpeggioportal/__version__.py
arpeggioportal/utils.py
arpeggioportal-0.0.1.dist-info/METADATA
arpeggioportal-0.0.1.dist-info/WHEEL
arpeggioportal-0.0.1.dist-info/top_level.txt
arpeggioportal-0.0.1.dist-info/RECORD
